pype3/__init__.py
pype3/build_helpers.py
pype3/csv_helpers.py
pype3/fargs.py
pype3/flask_helpers.py
pype3/func_helpers.py
pype3/hash_helpers.py
pype3/helpers.py
pype3/loaders.py
pype3/macros.py
pype3/nodes.py
pype3/numpy_helpers.py
pype3/string_helpers.py
pype3/time_helpers.py
pype3/trees.py
pype3/type_checking.py
pype3/vals.py
python_pype_lang_3-3.1.7.dist-info/LICENSE.txt
python_pype_lang_3-3.1.7.dist-info/METADATA
python_pype_lang_3-3.1.7.dist-info/WHEEL
python_pype_lang_3-3.1.7.dist-info/top_level.txt
python_pype_lang_3-3.1.7.dist-info/RECORD
