Metadata-Version: 2.1
Name: python-pype-lang-3
Version: 3.1.7
Summary: Version 3 of pype, a Python-integrated functional programming language - Provides easy-to-use pseudo-macros for common functional programming tasks such as maps, reduces, filters, conditionals, dictionary manipulations, and list manipulations..
Home-page: https://github.com/bbbbdragon/python-pype-lang-3.git
Author: Bennett Charles Bullock
Author-email: bennettbullock36@gmail.com
License: MIT
Keywords: functional programming map reduce filter lambda conditional
Platform: UNKNOWN
Classifier: Development Status :: 3 - Alpha
Classifier: License :: OSI Approved :: MIT License
Classifier: Programming Language :: Python :: 3.6
Classifier: Operating System :: OS Independent
Requires-Dist: cython
Requires-Dist: numpy
Requires-Dist: chardet
Requires-Dist: colorama
Requires-Dist: astpretty
Requires-Dist: mmh3
Requires-Dist: requests
Requires-Dist: flask
Requires-Dist: twine
Requires-Dist: python-dateutil
